private_db_llm/__init__.py
private_db_llm/config.py
private_db_llm/exceptions.py
private_db_llm/llm_client.py
private_db_llm/query_executor.py
private_db_llm/query_executor_pg.py
private_db_llm/schema_extractor.py
private_db_llm/schema_extractor_pg.py
private_db_llm/service.py
private_db_llm-0.1.1.dist-info/licenses/LICENSE
private_db_llm-0.1.1.dist-info/METADATA
private_db_llm-0.1.1.dist-info/WHEEL
private_db_llm-0.1.1.dist-info/top_level.txt
private_db_llm-0.1.1.dist-info/RECORD
