Metadata-Version: 2.4
Name: private-db-llm
Version: 0.1.1
Summary: Generate and execute SQL queries against MySQL/PostgreSQL using an LLM
Home-page: https://github.com/matinkhosravi/private-db-llm
Author: Matin Khosravi
Author-email: matinkhosravi97@gmail.com
Classifier: Programming Language :: Python :: 3
Classifier: License :: OSI Approved :: MIT License
Classifier: Operating System :: OS Independent
Requires-Python: >=3.8
License-File: LICENSE
Requires-Dist: mysql-connector-python>=8.0.0
Requires-Dist: openai>=1.0.0
Requires-Dist: httpx>=0.23.0
Requires-Dist: psycopg2-binary>=2.9.0
Dynamic: author
Dynamic: author-email
Dynamic: classifier
Dynamic: description
Dynamic: description-content-type
Dynamic: home-page
Dynamic: license-file
Dynamic: requires-dist
Dynamic: requires-python
Dynamic: summary
